<?xml version="1.0"?>
<!DOCTYPE hibernate-mapping PUBLIC "-//Hibernate/Hibernate Mapping DTD 3.0//EN"
"http://hibernate.sourceforge.net/hibernate-mapping-3.0.dtd">

<hibernate-mapping>
    <class name="com.mycompany.Member" table="MEMBER">
        <id name="id" type="java.lang.String">
            <column name="MEMBERID" />
            <generator class="native" />
        </id>
        <property name="username" type="java.lang.String">
            <column name="USERNAME" />
        </property>
        <property name="email" type="java.lang.String">
            <column name="EMAIL" />
        </property>
    </class>
</hibernate-mapping>
